qt_custom_treewidget/__init__.py
qt_custom_treewidget/custom.py
qt_custom_treewidget/integrated.py
qt_custom_treewidget-0.2.1.dist-info/METADATA
qt_custom_treewidget-0.2.1.dist-info/WHEEL
qt_custom_treewidget-0.2.1.dist-info/RECORD
