Metadata-Version: 2.1
Name: qt-custom-treewidget
Version: 0.2.1
Summary: 
Author: floris vernieuwe
Author-email: floris@vernieuwe.eu
Requires-Python: >=3.9,<4.0
Classifier: Programming Language :: Python :: 3
Classifier: Programming Language :: Python :: 3.9
Classifier: Programming Language :: Python :: 3.10
Classifier: Programming Language :: Python :: 3.11
Classifier: Programming Language :: Python :: 3.12
Classifier: Programming Language :: Python :: 3.13
Requires-Dist: qtpy (>=2.4.1,<3.0.0)
